{
	"addr": "46.174.52.185:27015",
	"gameport": 27015,
	"specport": 27020,
	"steamid": "85568392931362550",
	"name": "⚫️ PUBLIC | CRAZYPUB.RU | CS:GO | !viptest, скины",
	"appid": 730,
	"gamedir": "csgo",
	"version": "1.38.8.1",
	"product": "csgo",
	"region": -1,
	"players": 0,
	"max_players": 25,
	"bots": 1,
	"map": "de_mirage",
	"secure": true,
	"dedicated": true,
	"os": "l",
	"gametype": "empty,*grp:5114777i,128,128tick,? ?,awp,bhop,crazypub,cybershoke,dm,hsdm,idle,kz,mg,minigame,mirage,public,rus,russian,skins,su"
}