{
	"addr": "178.234.10.131:24018",
	"gameport": 24018,
	"steamid": "90200912485411841",
	"name": "TDZ | Maniac | 128tic",
	"appid": 730,
	"gamedir": "csgo",
	"version": "1.38.8.1",
	"product": "csgo",
	"region": -1,
	"players": 0,
	"max_players": 20,
	"bots": 0,
	"map": "/1232389954/hns_floppytown_v002",
	"secure": false,
	"dedicated": true,
	"os": "w",
	"gametype": "and,128tic,bluesen,ampr,!shop,!knife,!ws,128,!vip,dre,hide,hns,knife,hide and seek,maniac,man,myghetto,seek,shop,thm,tic,vip,ws"
}