{
	"addr": "185.188.183.107:51216",
	"gameport": 51216,
	"steamid": "85568392932076542",
	"name": "«JAIL»[BRCSGO.RU] ТЮРЬМА АРКХЕМ | [!WSGK !CASE]V2",
	"appid": 730,
	"gamedir": "csgo",
	"version": "1.40.2.6",
	"product": "csgo",
	"region": -1,
	"players": 1,
	"max_players": 32,
	"bots": 0,
	"map": "jb_summer_jail_v3",
	"secure": true,
	"dedicated": true,
	"os": "l",
	"gametype": "!,LastRequest,MyJailbreak,admin,awp,ba_,cyber,fb,gloves,jail,jailbreak,jb_,moscow,rus,russia,servertop,shop,top,vip,ws,secure"
}