{
	"addr": "185.234.72.3:27015",
	"gameport": 27015,
	"steamid": "90200163833683975",
	"name": "[CSGO] ★ GO.FIREON.RO ★ !WS !KNIFE !GLOVES !AGENTS !MUSIC !",
	"appid": 730,
	"gamedir": "csgo",
	"version": "1.38.8.1",
	"product": "csgo",
	"region": 3,
	"players": 0,
	"max_players": 32,
	"bots": 0,
	"map": "de_dust2",
	"secure": false,
	"dedicated": true,
	"os": "l",
	"gametype": "empty,!gloves,!knife,!skins,!ws,casual,compe,competitive,drop,free,gold,lvl,member,p,pro,rank,ranking,ro,romania,test,top,vip,v"
}